radioburst/radioburst.py
radioburst/setup.py
radioburst/utils.py
radioburst-0.1.42.dist-info/LICENSE
radioburst-0.1.42.dist-info/METADATA
radioburst-0.1.42.dist-info/WHEEL
radioburst-0.1.42.dist-info/top_level.txt
radioburst-0.1.42.dist-info/RECORD
